policy_validator/__init__.py
policy_validator/core.py
policy_validator/logging_setup.py
policy_validator-0.1.0.dist-info/LICENSE
policy_validator-0.1.0.dist-info/METADATA
policy_validator-0.1.0.dist-info/WHEEL
policy_validator-0.1.0.dist-info/top_level.txt
policy_validator-0.1.0.dist-info/RECORD
