Metadata-Version: 2.1
Name: policy_validator
Version: 0.1.0
Summary: A policy validation tool using OpenAI Models
Home-page: https://github.com/ashkanrafiee/policy_validator
Author: Ashkan Rafiee
Author-email: ashkanrafiee-pypi.cheer081@passmail.net
Keywords: openai,GPT,policy validation,content moderation
Classifier: Programming Language :: Python :: 3
Classifier: License :: OSI Approved :: MIT License
Classifier: Operating System :: OS Independent
Requires-Python: >=3.8
License-File: LICENSE
Requires-Dist: openai >=1.47.0
Requires-Dist: tenacity >=9.0.0
